{"nodes": [{"id": "c_users_brian_downloads_mivra_src_components_editor_editorcontext_tsx", "label": "EditorContext.tsx", "file_type": "code", "source_file": "C:\\Users\\Brian\\Downloads\\Mivra\\src\\components\\Editor\\EditorContext.tsx", "source_location": "L1"}, {"id": "editor_editorcontext_editorhandle", "label": "EditorHandle", "file_type": "code", "source_file": "C:\\Users\\Brian\\Downloads\\Mivra\\src\\components\\Editor\\EditorContext.tsx", "source_location": "L7"}, {"id": "editor_editorcontext_editorcontextvalue", "label": "EditorContextValue", "file_type": "code", "source_file": "C:\\Users\\Brian\\Downloads\\Mivra\\src\\components\\Editor\\EditorContext.tsx", "source_location": "L12"}, {"id": "editor_editorcontext_editorcontext", "label": "EditorContext", "file_type": "code", "source_file": "C:\\Users\\Brian\\Downloads\\Mivra\\src\\components\\Editor\\EditorContext.tsx", "source_location": "L16"}, {"id": "editor_editorcontext_editorprovider", "label": "EditorProvider()", "file_type": "code", "source_file": "C:\\Users\\Brian\\Downloads\\Mivra\\src\\components\\Editor\\EditorContext.tsx", "source_location": "L18"}, {"id": "editor_editorcontext_useeditorhandle", "label": "useEditorHandle()", "file_type": "code", "source_file": "C:\\Users\\Brian\\Downloads\\Mivra\\src\\components\\Editor\\EditorContext.tsx", "source_location": "L24"}], "edges": [{"source": "c_users_brian_downloads_mivra_src_components_editor_editorcontext_tsx", "target": "react", "relation": "imports_from", "context": "import", "confidence": "EXTRACTED", "source_file": "C:\\Users\\Brian\\Downloads\\Mivra\\src\\components\\Editor\\EditorContext.tsx", "source_location": "L1", "weight": 1.0}, {"source": "c_users_brian_downloads_mivra_src_components_editor_editorcontext_tsx", "target": "react", "relation": "imports_from", "context": "import", "confidence": "EXTRACTED", "source_file": "C:\\Users\\Brian\\Downloads\\Mivra\\src\\components\\Editor\\EditorContext.tsx", "source_location": "L2", "weight": 1.0}, {"source": "c_users_brian_downloads_mivra_src_components_editor_editorcontext_tsx", "target": "core", "relation": "imports_from", "context": "import", "confidence": "EXTRACTED", "source_file": "C:\\Users\\Brian\\Downloads\\Mivra\\src\\components\\Editor\\EditorContext.tsx", "source_location": "L3", "weight": 1.0}, {"source": "c_users_brian_downloads_mivra_src_components_editor_editorcontext_tsx", "target": "editor_editorcontext_editorhandle", "relation": "contains", "confidence": "EXTRACTED", "source_file": "C:\\Users\\Brian\\Downloads\\Mivra\\src\\components\\Editor\\EditorContext.tsx", "source_location": "L7", "weight": 1.0}, {"source": "c_users_brian_downloads_mivra_src_components_editor_editorcontext_tsx", "target": "editor_editorcontext_editorcontextvalue", "relation": "contains", "confidence": "EXTRACTED", "source_file": "C:\\Users\\Brian\\Downloads\\Mivra\\src\\components\\Editor\\EditorContext.tsx", "source_location": "L12", "weight": 1.0}, {"source": "c_users_brian_downloads_mivra_src_components_editor_editorcontext_tsx", "target": "editor_editorcontext_editorcontext", "relation": "contains", "confidence": "EXTRACTED", "source_file": "C:\\Users\\Brian\\Downloads\\Mivra\\src\\components\\Editor\\EditorContext.tsx", "source_location": "L16", "weight": 1.0}, {"source": "c_users_brian_downloads_mivra_src_components_editor_editorcontext_tsx", "target": "editor_editorcontext_editorprovider", "relation": "contains", "confidence": "EXTRACTED", "source_file": "C:\\Users\\Brian\\Downloads\\Mivra\\src\\components\\Editor\\EditorContext.tsx", "source_location": "L18", "weight": 1.0}, {"source": "c_users_brian_downloads_mivra_src_components_editor_editorcontext_tsx", "target": "editor_editorcontext_useeditorhandle", "relation": "contains", "confidence": "EXTRACTED", "source_file": "C:\\Users\\Brian\\Downloads\\Mivra\\src\\components\\Editor\\EditorContext.tsx", "source_location": "L24", "weight": 1.0}], "raw_calls": [{"caller_nid": "editor_editorcontext_editorprovider", "callee": "useRef", "is_member_call": false, "source_file": "C:\\Users\\Brian\\Downloads\\Mivra\\src\\components\\Editor\\EditorContext.tsx", "source_location": "L19"}, {"caller_nid": "editor_editorcontext_editorprovider", "callee": "useMemo", "is_member_call": false, "source_file": "C:\\Users\\Brian\\Downloads\\Mivra\\src\\components\\Editor\\EditorContext.tsx", "source_location": "L20"}, {"caller_nid": "editor_editorcontext_useeditorhandle", "callee": "useContext", "is_member_call": false, "source_file": "C:\\Users\\Brian\\Downloads\\Mivra\\src\\components\\Editor\\EditorContext.tsx", "source_location": "L25"}]}