{"nodes": [{"id": "c_users_brian_downloads_mivra_src_hooks_usemarkdownactions_ts", "label": "useMarkdownActions.ts", "file_type": "code", "source_file": "C:\\Users\\Brian\\Downloads\\Mivra\\src\\hooks\\useMarkdownActions.ts", "source_location": "L1"}, {"id": "hooks_usemarkdownactions_markdownaction", "label": "MarkdownAction", "file_type": "code", "source_file": "C:\\Users\\Brian\\Downloads\\Mivra\\src\\hooks\\useMarkdownActions.ts", "source_location": "L12"}, {"id": "hooks_usemarkdownactions_placeholders", "label": "Placeholders", "file_type": "code", "source_file": "C:\\Users\\Brian\\Downloads\\Mivra\\src\\hooks\\useMarkdownActions.ts", "source_location": "L27"}, {"id": "hooks_usemarkdownactions_ru_placeholders", "label": "RU_PLACEHOLDERS", "file_type": "code", "source_file": "C:\\Users\\Brian\\Downloads\\Mivra\\src\\hooks\\useMarkdownActions.ts", "source_location": "L38"}, {"id": "hooks_usemarkdownactions_en_placeholders", "label": "EN_PLACEHOLDERS", "file_type": "code", "source_file": "C:\\Users\\Brian\\Downloads\\Mivra\\src\\hooks\\useMarkdownActions.ts", "source_location": "L49"}, {"id": "hooks_usemarkdownactions_usemarkdownactions", "label": "useMarkdownActions()", "file_type": "code", "source_file": "C:\\Users\\Brian\\Downloads\\Mivra\\src\\hooks\\useMarkdownActions.ts", "source_location": "L64"}], "edges": [{"source": "c_users_brian_downloads_mivra_src_hooks_usemarkdownactions_ts", "target": "react", "relation": "imports_from", "context": "import", "confidence": "EXTRACTED", "source_file": "C:\\Users\\Brian\\Downloads\\Mivra\\src\\hooks\\useMarkdownActions.ts", "source_location": "L1", "weight": 1.0}, {"source": "c_users_brian_downloads_mivra_src_hooks_usemarkdownactions_ts", "target": "core", "relation": "imports_from", "context": "import", "confidence": "EXTRACTED", "source_file": "C:\\Users\\Brian\\Downloads\\Mivra\\src\\hooks\\useMarkdownActions.ts", "source_location": "L2", "weight": 1.0}, {"source": "c_users_brian_downloads_mivra_src_hooks_usemarkdownactions_ts", "target": "utils", "relation": "imports_from", "context": "import", "confidence": "EXTRACTED", "source_file": "C:\\Users\\Brian\\Downloads\\Mivra\\src\\hooks\\useMarkdownActions.ts", "source_location": "L3", "weight": 1.0}, {"source": "c_users_brian_downloads_mivra_src_hooks_usemarkdownactions_ts", "target": "plugin_dialog", "relation": "imports_from", "context": "import", "confidence": "EXTRACTED", "source_file": "C:\\Users\\Brian\\Downloads\\Mivra\\src\\hooks\\useMarkdownActions.ts", "source_location": "L4", "weight": 1.0}, {"source": "c_users_brian_downloads_mivra_src_hooks_usemarkdownactions_ts", "target": "plugin_fs", "relation": "imports_from", "context": "import", "confidence": "EXTRACTED", "source_file": "C:\\Users\\Brian\\Downloads\\Mivra\\src\\hooks\\useMarkdownActions.ts", "source_location": "L5", "weight": 1.0}, {"source": "c_users_brian_downloads_mivra_src_hooks_usemarkdownactions_ts", "target": "c_users_brian_downloads_mivra_src_stores_appstore_ts", "relation": "imports_from", "context": "import", "confidence": "EXTRACTED", "source_file": "C:\\Users\\Brian\\Downloads\\Mivra\\src\\hooks\\useMarkdownActions.ts", "source_location": "L7", "weight": 1.0}, {"source": "c_users_brian_downloads_mivra_src_hooks_usemarkdownactions_ts", "target": "stores_appstore_useappstore", "relation": "imports", "context": "import", "confidence": "EXTRACTED", "source_file": "C:\\Users\\Brian\\Downloads\\Mivra\\src\\hooks\\useMarkdownActions.ts", "source_location": "L7", "weight": 1.0}, {"source": "c_users_brian_downloads_mivra_src_hooks_usemarkdownactions_ts", "target": "c_users_brian_downloads_mivra_src_components_editor_editorcontext_tsx", "relation": "imports_from", "context": "import", "confidence": "EXTRACTED", "source_file": "C:\\Users\\Brian\\Downloads\\Mivra\\src\\hooks\\useMarkdownActions.ts", "source_location": "L8", "weight": 1.0}, {"source": "c_users_brian_downloads_mivra_src_hooks_usemarkdownactions_ts", "target": "editor_editorcontext_useeditorhandle", "relation": "imports", "context": "import", "confidence": "EXTRACTED", "source_file": "C:\\Users\\Brian\\Downloads\\Mivra\\src\\hooks\\useMarkdownActions.ts", "source_location": "L8", "weight": 1.0}, {"source": "c_users_brian_downloads_mivra_src_hooks_usemarkdownactions_ts", "target": "c_users_brian_downloads_mivra_src_utils_paths_ts", "relation": "imports_from", "context": "import", "confidence": "EXTRACTED", "source_file": "C:\\Users\\Brian\\Downloads\\Mivra\\src\\hooks\\useMarkdownActions.ts", "source_location": "L9", "weight": 1.0}, {"source": "c_users_brian_downloads_mivra_src_hooks_usemarkdownactions_ts", "target": "utils_paths_pickandformatasset", "relation": "imports", "context": "import", "confidence": "EXTRACTED", "source_file": "C:\\Users\\Brian\\Downloads\\Mivra\\src\\hooks\\useMarkdownActions.ts", "source_location": "L9", "weight": 1.0}, {"source": "c_users_brian_downloads_mivra_src_hooks_usemarkdownactions_ts", "target": "c_users_brian_downloads_mivra_src_hooks_uses3upload_ts", "relation": "imports_from", "context": "import", "confidence": "EXTRACTED", "source_file": "C:\\Users\\Brian\\Downloads\\Mivra\\src\\hooks\\useMarkdownActions.ts", "source_location": "L10", "weight": 1.0}, {"source": "c_users_brian_downloads_mivra_src_hooks_usemarkdownactions_ts", "target": "hooks_uses3upload_uses3upload", "relation": "imports", "context": "import", "confidence": "EXTRACTED", "source_file": "C:\\Users\\Brian\\Downloads\\Mivra\\src\\hooks\\useMarkdownActions.ts", "source_location": "L10", "weight": 1.0}, {"source": "c_users_brian_downloads_mivra_src_hooks_usemarkdownactions_ts", "target": "hooks_usemarkdownactions_markdownaction", "relation": "contains", "confidence": "EXTRACTED", "source_file": "C:\\Users\\Brian\\Downloads\\Mivra\\src\\hooks\\useMarkdownActions.ts", "source_location": "L12", "weight": 1.0}, {"source": "c_users_brian_downloads_mivra_src_hooks_usemarkdownactions_ts", "target": "hooks_usemarkdownactions_placeholders", "relation": "contains", "confidence": "EXTRACTED", "source_file": "C:\\Users\\Brian\\Downloads\\Mivra\\src\\hooks\\useMarkdownActions.ts", "source_location": "L27", "weight": 1.0}, {"source": "c_users_brian_downloads_mivra_src_hooks_usemarkdownactions_ts", "target": "hooks_usemarkdownactions_ru_placeholders", "relation": "contains", "confidence": "EXTRACTED", "source_file": "C:\\Users\\Brian\\Downloads\\Mivra\\src\\hooks\\useMarkdownActions.ts", "source_location": "L38", "weight": 1.0}, {"source": "c_users_brian_downloads_mivra_src_hooks_usemarkdownactions_ts", "target": "hooks_usemarkdownactions_en_placeholders", "relation": "contains", "confidence": "EXTRACTED", "source_file": "C:\\Users\\Brian\\Downloads\\Mivra\\src\\hooks\\useMarkdownActions.ts", "source_location": "L49", "weight": 1.0}, {"source": "c_users_brian_downloads_mivra_src_hooks_usemarkdownactions_ts", "target": "hooks_usemarkdownactions_usemarkdownactions", "relation": "contains", "confidence": "EXTRACTED", "source_file": "C:\\Users\\Brian\\Downloads\\Mivra\\src\\hooks\\useMarkdownActions.ts", "source_location": "L64", "weight": 1.0}], "raw_calls": [{"caller_nid": "hooks_usemarkdownactions_usemarkdownactions", "callee": "useEditorHandle", "is_member_call": false, "source_file": "C:\\Users\\Brian\\Downloads\\Mivra\\src\\hooks\\useMarkdownActions.ts", "source_location": "L65"}, {"caller_nid": "hooks_usemarkdownactions_usemarkdownactions", "callee": "useAppStore", "is_member_call": false, "source_file": "C:\\Users\\Brian\\Downloads\\Mivra\\src\\hooks\\useMarkdownActions.ts", "source_location": "L66"}, {"caller_nid": "hooks_usemarkdownactions_usemarkdownactions", "callee": "useAppStore", "is_member_call": false, "source_file": "C:\\Users\\Brian\\Downloads\\Mivra\\src\\hooks\\useMarkdownActions.ts", "source_location": "L67"}, {"caller_nid": "hooks_usemarkdownactions_usemarkdownactions", "callee": "useAppStore", "is_member_call": false, "source_file": "C:\\Users\\Brian\\Downloads\\Mivra\\src\\hooks\\useMarkdownActions.ts", "source_location": "L68"}, {"caller_nid": "hooks_usemarkdownactions_usemarkdownactions", "callee": "useAppStore", "is_member_call": false, "source_file": "C:\\Users\\Brian\\Downloads\\Mivra\\src\\hooks\\useMarkdownActions.ts", "source_location": "L69"}, {"caller_nid": "hooks_usemarkdownactions_usemarkdownactions", "callee": "useMemo", "is_member_call": false, "source_file": "C:\\Users\\Brian\\Downloads\\Mivra\\src\\hooks\\useMarkdownActions.ts", "source_location": "L71"}, {"caller_nid": "hooks_usemarkdownactions_usemarkdownactions", "callee": "useCallback", "is_member_call": false, "source_file": "C:\\Users\\Brian\\Downloads\\Mivra\\src\\hooks\\useMarkdownActions.ts", "source_location": "L76"}, {"caller_nid": "hooks_usemarkdownactions_usemarkdownactions", "callee": "useCallback", "is_member_call": false, "source_file": "C:\\Users\\Brian\\Downloads\\Mivra\\src\\hooks\\useMarkdownActions.ts", "source_location": "L142"}, {"caller_nid": "hooks_usemarkdownactions_usemarkdownactions", "callee": "useS3Upload", "is_member_call": false, "source_file": "C:\\Users\\Brian\\Downloads\\Mivra\\src\\hooks\\useMarkdownActions.ts", "source_location": "L150"}, {"caller_nid": "hooks_usemarkdownactions_usemarkdownactions", "callee": "useCallback", "is_member_call": false, "source_file": "C:\\Users\\Brian\\Downloads\\Mivra\\src\\hooks\\useMarkdownActions.ts", "source_location": "L154"}]}